[
	{
		"Id": "accept",
		"Name": "accept",
		"Global": false,
		"AttributeType": "AttributeMultiValue",
		"ValueTester": "pvc\\html\\val_tester\\MediaTypeTester",
		"CaseSensitive": false
	},
	{
		"Id": "accept-charset",
		"Name": "accept-charset",
		"Global": false,
		"AttributeType": "AttributeMultiValue",
		"ValueTester": "charsetTester",
		"CaseSensitive": false
	},
	{
		"Id": "accesskey",
		"Name": "accesskey",
		"Global": true,
		"AttributeType": "AttributeSingleValue",
		"ValueTester": "accessKeyTester",
		"CaseSensitive": false
	},
	{
		"Id": "action",
		"Name": "action",
		"Global": false,
		"AttributeType": "AttributeSingleValue",
		"ValueTester": "urlTester",
		"CaseSensitive": false
	},
	{
		"Id": "alt",
		"Name": "alt",
		"Global": false,
		"AttributeType": "AttributeSingleValue",
		"ValueTester": "pvc\\validator\\val_tester\\ctype\\CTypeTesterPrintable",
		"CaseSensitive": false
	},
	{
		"Id": "async",
		"Name": "async",
		"Global": false,
		"AttributeType": "AttributeVoid",
		"ValueTester": "",
		"CaseSensitive": false
	},
	{
		"Id": "autocomplete",
		"Name": "autocomplete",
		"Global": false,
		"AttributeType": "AttributeSingleValue",
		"ValueTester": "autocompleteTester",
		"CaseSensitive": false
	},
	{
		"Id": "autofocus",
		"Name": "autofocus",
		"Global": false,
		"AttributeType": "AttributeVoid",
		"ValueTester": "",
		"CaseSensitive": false
	},
	{
		"Id": "charset",
		"Name": "charset",
		"Global": false,
		"AttributeType": "AttributeSingleValue",
		"ValueTester": "charsetTester",
		"CaseSensitive": false
	},
	{
		"Id": "checked",
		"Name": "checked",
		"Global": false,
		"AttributeType": "AttributeVoid",
		"ValueTester": "",
		"CaseSensitive": false
	},
	{
		"Id": "cite",
		"Name": "cite",
		"Global": false,
		"AttributeType": "AttributeSingleValue",
		"ValueTester": "urlTester",
		"CaseSensitive": false
	},
	{
		"Id": "class",
		"Name": "class",
		"Global": true,
		"AttributeType": "AttributeMultiValue",
		"ValueTester": "cssClassTester",
		"CaseSensitive": false
	},
	{
		"Id": "cols",
		"Name": "cols",
		"Global": false,
		"AttributeType": "AttributeSingleValue",
		"ValueTester": "positiveIntegerSimpleTester",
		"CaseSensitive": false
	},
	{
		"Id": "colspan",
		"Name": "colspan",
		"Global": false,
		"AttributeType": "AttributeSingleValue",
		"ValueTester": "positiveIntegerSimpleTester",
		"CaseSensitive": false
	},
	{
		"Id": "content",
		"Name": "content",
		"Global": false,
		"AttributeType": "AttributeSingleValue",
		"ValueTester": "pvc\\validator\\val_tester\\always_true\\AlwaysTrueTester",
		"CaseSensitive": false
	},
	{
		"Id": "contenteditable",
		"Name": "contenteditable",
		"Global": true,
		"AttributeType": "AttributeSingleValue",
		"ValueTester": "trueFalseTester",
		"CaseSensitive": false
	},
	{
		"Id": "controls",
		"Name": "controls",
		"Global": false,
		"AttributeType": "AttributeVoid",
		"ValueTester": "",
		"CaseSensitive": false
	},
	{
		"Id": "coords",
		"Name": "coords",
		"Global": false,
		"AttributeType": "AttributeSingleValue",
		"ValueTester": "pvc\\html\\val_tester\\AreaCoordsTester",
		"CaseSensitive": false
	},
	{
		"Id": "crossorigin",
		"Name": "crossorigin",
		"Global": false,
		"AttributeType": "AttributeSingleValue",
		"ValueTester": "crossOriginTester",
		"CaseSensitive": false
	},
	{
		"Id": "data",
		"Name": "data",
		"Global": false,
		"AttributeType": "AttributeSingleValue",
		"ValueTester": "urlTester",
		"CaseSensitive": false
	},
	{
		"Id": "datetime",
		"Name": "datetime",
		"Global": false,
		"AttributeType": "AttributeSingleValue",
		"ValueTester": "javascriptDateTimeTester",
		"CaseSensitive": false
	},
	{
		"Id": "default",
		"Name": "default",
		"Global": false,
		"AttributeType": "AttributeVoid",
		"ValueTester": "",
		"CaseSensitive": false
	},
	{
		"Id": "defer",
		"Name": "defer",
		"Global": false,
		"AttributeType": "AttributeVoid",
		"ValueTester": "",
		"CaseSensitive": false
	},
	{
		"Id": "dir",
		"Name": "dir",
		"Global": true,
		"AttributeType": "AttributeSingleValue",
		"ValueTester": "textDirectionTester",
		"CaseSensitive": false
	},
	{
		"Id": "dirname",
		"Name": "dirname",
		"Global": false,
		"AttributeType": "AttributeSingleValue",
		"ValueTester": "pvc\\validator\\val_tester\\always_true\\AlwaysTrueTester",
		"CaseSensitive": false
	},
	{
		"Id": "disabled",
		"Name": "disabled",
		"Global": false,
		"AttributeType": "AttributeVoid",
		"ValueTester": "",
		"CaseSensitive": false
	},
	{
		"Id": "download",
		"Name": "download",
		"Global": false,
		"AttributeType": "AttributeSingleValue",
		"ValueTester": "",
		"CaseSensitive": false
	},
	{
		"Id": "draggable",
		"Name": "draggable",
		"Global": true,
		"AttributeType": "AttributeSingleValue",
		"ValueTester": "yesNoTester",
		"CaseSensitive": false
	},
	{
		"Id": "enctype",
		"Name": "enctype",
		"Global": false,
		"AttributeType": "AttributeSingleValue",
		"ValueTester": "encTypeTester",
		"CaseSensitive": false
	},
	{
		"Id": "enterkeyhint",
		"Name": "enterkeyhint",
		"Global": true,
		"AttributeType": "AttributeSingleValue",
		"ValueTester": "pvc\\validator\\val_tester\\always_true\\AlwaysTrueTester",
		"CaseSensitive": false
	},
	{
		"Id": "for",
		"Name": "for",
		"Global": false,
		"AttributeType": "AttributeMultiValue",
		"ValueTester": "pvc\\validator\\val_tester\\always_true\\AlwaysTrueTester",
		"CaseSensitive": false
	},
	{
		"Id": "form",
		"Name": "form",
		"Global": false,
		"AttributeType": "AttributeSingleValue",
		"ValueTester": "pvc\\validator\\val_tester\\always_true\\AlwaysTrueTester",
		"CaseSensitive": false
	},
	{
		"Id": "formaction",
		"Name": "formaction",
		"Global": false,
		"AttributeType": "AttributeSingleValue",
		"ValueTester": "urlTester",
		"CaseSensitive": false
	},
	{
		"Id": "formnovalidate",
		"Name": "formnovalidate",
		"Global": false,
		"AttributeType": "AttributeVoid",
		"ValueTester": "",
		"CaseSensitive": false
	},
	{
		"Id": "headers",
		"Name": "headers",
		"Global": false,
		"AttributeType": "AttributeSingleValue",
		"ValueTester": "pvc\\validator\\val_tester\\always_true\\AlwaysTrueTester",
		"CaseSensitive": false
	},
	{
		"Id": "height",
		"Name": "height",
		"Global": false,
		"AttributeType": "AttributeSingleValue",
		"ValueTester": "positiveIntegerSimpleTester",
		"CaseSensitive": false
	},
	{
		"Id": "hidden",
		"Name": "hidden",
		"Global": true,
		"AttributeType": "AttributeVoid",
		"ValueTester": "",
		"CaseSensitive": false
	},
	{
		"Id": "high",
		"Name": "high",
		"Global": false,
		"AttributeType": "AttributeSingleValue",
		"ValueTester": "positiveIntegerSimpleTester",
		"CaseSensitive": false
	},
	{
		"Id": "href",
		"Name": "href",
		"Global": false,
		"AttributeType": "AttributeSingleValue",
		"ValueTester": "urlTester",
		"CaseSensitive": false
	},
	{
		"Id": "hreflang",
		"Name": "hreflang",
		"Global": false,
		"AttributeType": "AttributeSingleValue",
		"ValueTester": "languageCodeTester",
		"CaseSensitive": false
	},
	{
		"Id": "http-equiv",
		"Name": "http-equiv",
		"Global": false,
		"AttributeType": "AttributeSingleValue",
		"ValueTester": "pvc\\validator\\val_tester\\always_true\\AlwaysTrueTester",
		"CaseSensitive": false
	},
	{
		"Id": "id",
		"Name": "id",
		"Global": true,
		"AttributeType": "AttributeSingleValue",
		"ValueTester": "htmlIdNameTester",
		"CaseSensitive": true
	},
	{
		"Id": "inert",
		"Name": "inert",
		"Global": false,
		"AttributeType": "AttributeVoid",
		"ValueTester": "",
		"CaseSensitive": false
	},
	{
		"Id": "inputmode",
		"Name": "inputmode",
		"Global": false,
		"AttributeType": "AttributeSingleValue",
		"ValueTester": "inputModeTester",
		"CaseSensitive": false
	},
	{
		"Id": "ismap",
		"Name": "ismap",
		"Global": false,
		"AttributeType": "AttributeVoid",
		"ValueTester": "",
		"CaseSensitive": false
	},
	{
		"Id": "itemscope",
		"Name": "itemscope",
		"Global": false,
		"AttributeType": "AttributeVoid",
		"ValueTester": "",
		"CaseSensitive": false
	},
	{
		"Id": "kind",
		"Name": "kind",
		"Global": false,
		"AttributeType": "AttributeSingleValue",
		"ValueTester": "pvc\\validator\\val_tester\\always_true\\AlwaysTrueTester",
		"CaseSensitive": false
	},
	{
		"Id": "label",
		"Name": "label",
		"Global": false,
		"AttributeType": "AttributeSingleValue",
		"ValueTester": "",
		"CaseSensitive": false
	},
	{
		"Id": "lang",
		"Name": "lang",
		"Global": true,
		"AttributeType": "AttributeSingleValue",
		"ValueTester": "languageCodeTester",
		"CaseSensitive": false
	},
	{
		"Id": "list",
		"Name": "list",
		"Global": false,
		"AttributeType": "AttributeSingleValue",
		"ValueTester": "pvc\\validator\\val_tester\\always_true\\AlwaysTrueTester",
		"CaseSensitive": false
	},
	{
		"Id": "loop",
		"Name": "loop",
		"Global": false,
		"AttributeType": "AttributeVoid",
		"ValueTester": "",
		"CaseSensitive": false
	},
	{
		"Id": "low",
		"Name": "low",
		"Global": false,
		"AttributeType": "AttributeSingleValue",
		"ValueTester": "positiveIntegerSimpleTester",
		"CaseSensitive": false
	},
	{
		"Id": "max",
		"Name": "max",
		"Global": false,
		"AttributeType": "AttributeSingleValue",
		"ValueTester": "positiveIntegerSimpleTester",
		"CaseSensitive": false
	},
	{
		"Id": "maxlength",
		"Name": "maxlength",
		"Global": false,
		"AttributeType": "AttributeSingleValue",
		"ValueTester": "positiveIntegerSimpleTester",
		"CaseSensitive": false
	},
	{
		"Id": "media",
		"Name": "media",
		"Global": false,
		"AttributeType": "AttributeSingleValue",
		"ValueTester": "pvc\\validator\\val_tester\\always_true\\AlwaysTrueTester",
		"CaseSensitive": false
	},
	{
		"Id": "method",
		"Name": "method",
		"Global": false,
		"AttributeType": "AttributeSingleValue",
		"ValueTester": "methodTypeTester",
		"CaseSensitive": false
	},
	{
		"Id": "min",
		"Name": "min",
		"Global": false,
		"AttributeType": "AttributeSingleValue",
		"ValueTester": "positiveIntegerSimpleTester",
		"CaseSensitive": false
	},
	{
		"Id": "multiple",
		"Name": "multiple",
		"Global": false,
		"AttributeType": "AttributeVoid",
		"ValueTester": "",
		"CaseSensitive": false
	},
	{
		"Id": "muted",
		"Name": "muted",
		"Global": false,
		"AttributeType": "AttributeVoid",
		"ValueTester": "",
		"CaseSensitive": false
	},
	{
		"Id": "name",
		"Name": "name",
		"Global": false,
		"AttributeType": "AttributeSingleValue",
		"ValueTester": "htmlIdNameTester",
		"CaseSensitive": true
	},
	{
		"Id": "nomodule",
		"Name": "nomodule",
		"Global": false,
		"AttributeType": "AttributeVoid",
		"ValueTester": "",
		"CaseSensitive": false
	},
	{
		"Id": "novalidate",
		"Name": "novalidate",
		"Global": false,
		"AttributeType": "AttributeVoid",
		"ValueTester": "",
		"CaseSensitive": false
	},
	{
		"Id": "open",
		"Name": "open",
		"Global": false,
		"AttributeType": "AttributeVoid",
		"ValueTester": "",
		"CaseSensitive": false
	},
	{
		"Id": "optimum",
		"Name": "optimum",
		"Global": false,
		"AttributeType": "AttributeSingleValue",
		"ValueTester": "positiveIntegerSimpleTester",
		"CaseSensitive": false
	},
	{
		"Id": "pattern",
		"Name": "pattern",
		"Global": false,
		"AttributeType": "AttributeSingleValue",
		"ValueTester": "regexPatternTester",
		"CaseSensitive": false
	},
	{
		"Id": "ping",
		"Name": "ping",
		"Global": false,
		"AttributeType": "AttributeMultiValue",
		"ValueTester": "urlTester",
		"CaseSensitive": false
	},
	{
		"Id": "placeholder",
		"Name": "placeholder",
		"Global": false,
		"AttributeType": "AttributeSingleValue",
		"ValueTester": "pvc\\validator\\val_tester\\always_true\\AlwaysTrueTester",
		"CaseSensitive": false
	},
	{
		"Id": "playsinline",
		"Name": "playsinline",
		"Global": false,
		"AttributeType": "AttributeVoid",
		"ValueTester": "",
		"CaseSensitive": false
	},
	{
		"Id": "popover",
		"Name": "popover",
		"Global": true,
		"AttributeType": "AttributeVoid",
		"ValueTester": "",
		"CaseSensitive": false
	},
	{
		"Id": "popovertarget",
		"Name": "popovertarget",
		"Global": false,
		"AttributeType": "AttributeSingleValue",
		"ValueTester": "htmlIdNameTester",
		"CaseSensitive": false
	},
	{
		"Id": "popovertargetaction",
		"Name": "popovertargetaction",
		"Global": false,
		"AttributeType": "AttributeSingleValue",
		"ValueTester": "popoverTargetActionTester",
		"CaseSensitive": false
	},
	{
		"Id": "poster",
		"Name": "poster",
		"Global": false,
		"AttributeType": "AttributeSingleValue",
		"ValueTester": "urlTester",
		"CaseSensitive": false
	},
	{
		"Id": "preload",
		"Name": "preload",
		"Global": false,
		"AttributeType": "AttributeSingleValue",
		"ValueTester": "preloadTester",
		"CaseSensitive": false
	},
	{
		"Id": "readonly",
		"Name": "readonly",
		"Global": false,
		"AttributeType": "AttributeVoid",
		"ValueTester": "",
		"CaseSensitive": false
	},
	{
		"Id": "referrerpolicy",
		"Name": "referrerpolicy",
		"Global": false,
		"AttributeType": "AttributeSingleValue",
		"ValueTester": "referrerPolicyTester",
		"CaseSensitive": false
	},
	{
		"Id": "rel",
		"Name": "rel",
		"Global": false,
		"AttributeType": "AttributeSingleValue",
		"ValueTester": "relChoiceTester",
		"CaseSensitive": false
	},
	{
		"Id": "required",
		"Name": "required",
		"Global": false,
		"AttributeType": "AttributeVoid",
		"ValueTester": "",
		"CaseSensitive": false
	},
	{
		"Id": "reversed",
		"Name": "reversed",
		"Global": false,
		"AttributeType": "AttributeVoid",
		"ValueTester": "",
		"CaseSensitive": false
	},
	{
		"Id": "rows",
		"Name": "rows",
		"Global": false,
		"AttributeType": "AttributeSingleValue",
		"ValueTester": "positiveIntegerSimpleTester",
		"CaseSensitive": false
	},
	{
		"Id": "rowspan",
		"Name": "rowspan",
		"Global": false,
		"AttributeType": "AttributeSingleValue",
		"ValueTester": "positiveIntegerSimpleTester",
		"CaseSensitive": false
	},
	{
		"Id": "sandbox",
		"Name": "sandbox",
		"Global": false,
		"AttributeType": "AttributeMultiValue",
		"ValueTester": "sandBoxChoiceTester",
		"CaseSensitive": false
	},
	{
		"Id": "scope",
		"Name": "scope",
		"Global": false,
		"AttributeType": "AttributeSingleValue",
		"ValueTester": "scopeTester",
		"CaseSensitive": false
	},
	{
		"Id": "selected",
		"Name": "selected",
		"Global": false,
		"AttributeType": "AttributeVoid",
		"ValueTester": "",
		"CaseSensitive": false
	},
	{
		"Id": "shape",
		"Name": "shape",
		"Global": false,
		"AttributeType": "AttributeSingleValue",
		"ValueTester": "shapeTester",
		"CaseSensitive": false
	},
	{
		"Id": "size",
		"Name": "size",
		"Global": false,
		"AttributeType": "AttributeSingleValue",
		"ValueTester": "positiveIntegerSimpleTester",
		"CaseSensitive": false
	},
	{
		"Id": "sizes",
		"Name": "sizes",
		"Global": false,
		"AttributeType": "AttributeSingleValue",
		"ValueTester": "sizesTester",
		"CaseSensitive": false
	},
	{
		"Id": "span",
		"Name": "span",
		"Global": false,
		"AttributeType": "AttributeSingleValue",
		"ValueTester": "positiveIntegerSimpleTester",
		"CaseSensitive": false
	},
	{
		"Id": "spellcheck",
		"Name": "spellcheck",
		"Global": false,
		"AttributeType": "AttributeSingleValue",
		"ValueTester": "trueFalseTester",
		"CaseSensitive": false
	},
	{
		"Id": "src",
		"Name": "src",
		"Global": false,
		"AttributeType": "AttributeSingleValue",
		"ValueTester": "urlTester",
		"CaseSensitive": false
	},
	{
		"Id": "srcdoc",
		"Name": "srcdoc",
		"Global": false,
		"AttributeType": "AttributeSingleValue",
		"ValueTester": "pvc\\validator\\val_tester\\always_true\\AlwaysTrueTester",
		"CaseSensitive": false
	},
	{
		"Id": "srclang",
		"Name": "srclang",
		"Global": false,
		"AttributeType": "AttributeSingleValue",
		"ValueTester": "languageCodeTester",
		"CaseSensitive": false
	},
	{
		"Id": "srcset",
		"Name": "srcset",
		"Global": false,
		"AttributeType": "AttributeSingleValue",
		"ValueTester": "urlTester",
		"CaseSensitive": false
	},
	{
		"Id": "start",
		"Name": "start",
		"Global": false,
		"AttributeType": "AttributeSingleValue",
		"ValueTester": "positiveIntegerSimpleTester",
		"CaseSensitive": false
	},
	{
		"Id": "step",
		"Name": "step",
		"Global": false,
		"AttributeType": "AttributeSingleValue",
		"ValueTester": "positiveIntegerSimpleTester",
		"CaseSensitive": false
	},
	{
		"Id": "style",
		"Name": "style",
		"Global": false,
		"AttributeType": "AttributeSingleValue",
		"ValueTester": "pvc\\validator\\val_tester\\always_true\\AlwaysTrueTester",
		"CaseSensitive": false
	},
	{
		"Id": "tabindex",
		"Name": "tabindex",
		"Global": true,
		"AttributeType": "AttributeSingleValue",
		"ValueTester": "positiveIntegerSimpleTester",
		"CaseSensitive": false
	},
	{
		"Id": "target",
		"Name": "target",
		"Global": false,
		"AttributeType": "AttributeSingleValue",
		"ValueTester": "targetTester",
		"CaseSensitive": false
	},
	{
		"Id": "title",
		"Name": "title",
		"Global": false,
		"AttributeType": "AttributeSingleValue",
		"ValueTester": "pvc\\html\\val_tester\\TitleTester",
		"CaseSensitive": false
	},
	{
		"Id": "translate",
		"Name": "translate",
		"Global": true,
		"AttributeType": "AttributeSingleValue",
		"ValueTester": "yesNoTester",
		"CaseSensitive": false
	},
	{
		"Id": "buttontype",
		"Name": "type",
		"Global": false,
		"AttributeType": "AttributeSingleValue",
		"ValueTester": "buttonTypeTester",
		"CaseSensitive": false
	},
	{
		"Id": "inputtype",
		"Name": "type",
		"Global": false,
		"AttributeType": "AttributeSingleValue",
		"ValueTester": "inputTypeTester",
		"CaseSensitive": false
	},
	{
		"Id": "mimetype",
		"Name": "mimetype",
		"Global": false,
		"AttributeType": "AttributeSingleValue",
		"ValueTester": "pvc\\html\\val_tester\\MediaTypeTester",
		"CaseSensitive": false
	},
	{
		"Id": "usemap",
		"Name": "usemap",
		"Global": false,
		"AttributeType": "AttributeSingleValue",
		"ValueTester": "pvc\\validator\\val_tester\\always_true\\AlwaysTrueTester",
		"CaseSensitive": false
	},
	{
		"Id": "value",
		"Name": "value",
		"Global": false,
		"AttributeType": "AttributeSingleValue",
		"ValueTester": "pvc\\validator\\val_tester\\always_true\\AlwaysTrueTester",
		"CaseSensitive": false
	},
	{
		"Id": "width",
		"Name": "width",
		"Global": false,
		"AttributeType": "AttributeSingleValue",
		"ValueTester": "positiveIntegerSimpleTester",
		"CaseSensitive": false
	},
	{
		"Id": "wrap",
		"Name": "wrap",
		"Global": false,
		"AttributeType": "AttributeSingleValue",
		"ValueTester": "wrapTester",
		"CaseSensitive": false
	},
	{
		"Id": "xmlns",
		"Name": "xmlns",
		"Global": false,
		"AttributeType": "AttributeSingleValue",
		"ValueTester": "xmlnsTester",
		"CaseSensitive": false
	}
]